OGU/__init__.py
OGU/__main__.py
OGU/cli.py
OGU/evaluate.py
OGU/gb2fasta.py
OGU/global_vars.py
OGU/primer.py
OGU/ui.py
OGU/utils.py
OGU/visualize.py
OGU/data/angiosperm_cp_Evaluation.csv
OGU/data/animal_orders.csv
OGU/data/button1.png
OGU/data/button2.png
OGU/data/button3.png
OGU/data/button4.png
OGU/data/classes.csv
OGU/data/draw_circle_mitochondria.ipynb
OGU/data/draw_circle_plastid.ipynb
OGU/data/kingdoms.csv
OGU/data/phyla.csv
OGU/data/rodents_mt_Evaluation.csv
OGU/data/rodents_mt_extend.gb
OGU/data/superkingdoms.csv
OGU/data/tobacco_cp_extend.gb
ogu-2.0.2.dist-info/METADATA
ogu-2.0.2.dist-info/WHEEL
ogu-2.0.2.dist-info/entry_points.txt
ogu-2.0.2.dist-info/licenses/LICENSE
ogu-2.0.2.dist-info/RECORD
