Metadata-Version: 2.4
Name: OGU
Version: 2.0.2
Summary: Organelle Genome Utilities
Project-URL: Homepage, https://github.com/wpwupingwp/OGU
Project-URL: Bug Tracker, https://github.com/wpwupingwp/OGU/issues
Author-email: Ping Wu <wpwupingwp@outlook.com>
Maintainer-email: Ping Wu <wpwupingwp@outlook.com>
License: AGPL-3.0-or-later
License-File: LICENSE
Keywords: Bioinformatics,analysis,mitochondria,organelle genome,plastid
Classifier: Development Status :: 5 - Production/Stable
Classifier: Intended Audience :: Developers
Classifier: Intended Audience :: Science/Research
Classifier: License :: OSI Approved :: GNU Affero General Public License v3
Classifier: Operating System :: MacOS :: MacOS X
Classifier: Operating System :: Microsoft :: Windows
Classifier: Operating System :: POSIX
Classifier: Programming Language :: Python :: 3.10
Classifier: Topic :: Scientific/Engineering :: Bio-Informatics
Requires-Python: >=3.9
Requires-Dist: biopython>=1.85
Requires-Dist: certifi>=2024.12.14
Requires-Dist: colorama>=0.4.6
Requires-Dist: coloredlogs>=10.0
Requires-Dist: matplotlib>=3.0.0
Requires-Dist: numpy>=2.0
Requires-Dist: pandas>=2.1.4
Requires-Dist: primer3-py>=2.0.2
Requires-Dist: pycirclize>=1.7.1
